pywiktionary/__init__.py
pywiktionary/wiktionary_parser_factory.py
pywiktionary/parsers/__init__.py
pywiktionary/parsers/basic_parser.py
pywiktionary/parsers/english_parser.py
pywiktionary/parsers/italian_parser.py
pywiktionary-0.4a1.post1.dist-info/LICENSE
pywiktionary-0.4a1.post1.dist-info/METADATA
pywiktionary-0.4a1.post1.dist-info/WHEEL
pywiktionary-0.4a1.post1.dist-info/top_level.txt
pywiktionary-0.4a1.post1.dist-info/RECORD
