Metadata-Version: 2.1
Name: pywiktionary
Version: 0.4a1.post1
Summary: Python library to retrieve wiktionary word definitions for different languages
Home-page: UNKNOWN
Author: Alessandro Mesti
Author-email: mesti.alessandro@gmail.com
License: UNKNOWN
Project-URL: Code, https://github.com/alessandrome/pywiktionary
Keywords: w,i,k,t,i,o,n,a,r,y, ,p,a,r,s,e,r, ,s,c,r,a,p,e,r, ,w,o,r,d, ,w,o,r,d,s, ,m,u,l,t,i,l,i,n,g,u,a,l
Platform: UNKNOWN
Classifier: Programming Language :: Python :: 3
Classifier: License :: OSI Approved :: MIT License
Classifier: Operating System :: OS Independent
Classifier: Development Status :: 3 - Alpha
Classifier: Intended Audience :: Developers
Classifier: Topic :: Text Processing
Classifier: Topic :: Text Processing :: Linguistic
Classifier: Topic :: Text Processing :: Markup :: HTML
Requires-Dist: requests (<3,>=2)
Requires-Dist: BeautifulSoup4 (>=4)
